Metadata-Version: 2.4
Name: flake8-black
Version: 0.4.0
Summary: flake8 plugin to call black as a code style validator
Author: Peter J. A. Cock
Maintainer-email: "Peter J. A. Cock" <p.j.a.cock@googlemail.com>
License: MIT
Project-URL: Homepage, https://github.com/peterjc/flake8-black
Project-URL: Source Code, https://github.com/peterjc/flake8-black/
Project-URL: Bug Tracker, https://github.com/peterjc/flake8-black/issues
Project-URL: Documentation, https://github.com/peterjc/flake8-black/blob/master/README.rst
Keywords: black,formatting,style,flake8
Classifier: Intended Audience :: Developers
Classifier: Framework :: Flake8
Classifier: License :: OSI Approved :: MIT License
Classifier: Operating System :: OS Independent
Classifier: Topic :: Software Development :: Libraries :: Python Modules
Classifier: Topic :: Software Development :: Quality Assurance
Classifier: Programming Language :: Python
Classifier: Programming Language :: Python :: 3
Classifier: Programming Language :: Python :: 3 :: Only
Requires-Python: >=3.9
License-File: LICENSE.rst
Requires-Dist: flake8>=3
Requires-Dist: black>=22.1.0
Requires-Dist: tomli; python_version < "3.11"
Provides-Extra: develop
Requires-Dist: build; extra == "develop"
Requires-Dist: twine; extra == "develop"
Dynamic: license-file
